oqupy/__init__.py
oqupy/base_api.py
oqupy/bath.py
oqupy/bath_correlations.py
oqupy/bath_dynamics.py
oqupy/config.py
oqupy/control.py
oqupy/dynamics.py
oqupy/gradient.py
oqupy/helpers.py
oqupy/mps_mpo.py
oqupy/operators.py
oqupy/process_tensor.py
oqupy/pt_tebd.py
oqupy/pt_tempo.py
oqupy/system.py
oqupy/system_dynamics.py
oqupy/tempo.py
oqupy/util.py
oqupy/version.py
oqupy/backends/__init__.py
oqupy/backends/node_array.py
oqupy/backends/pt_tebd_backend.py
oqupy/backends/pt_tempo_backend.py
oqupy/backends/tempo_backend.py
oqupy-0.5.0.dist-info/AUTHORS.md
oqupy-0.5.0.dist-info/LICENSE
oqupy-0.5.0.dist-info/METADATA
oqupy-0.5.0.dist-info/WHEEL
oqupy-0.5.0.dist-info/top_level.txt
oqupy-0.5.0.dist-info/RECORD
